gurux_dlms/ActionRequestType.py
gurux_dlms/ActionResponseType.py
gurux_dlms/AesGcmParameter.py
gurux_dlms/ConfirmedServiceError.py
gurux_dlms/ConnectionState.py
gurux_dlms/CountType.py
gurux_dlms/GXArray.py
gurux_dlms/GXBitString.py
gurux_dlms/GXByteBuffer.py
gurux_dlms/GXCiphering.py
gurux_dlms/GXCryptoKeyParameter.py
gurux_dlms/GXDLMS.py
gurux_dlms/GXDLMSAccessItem.py
gurux_dlms/GXDLMSChippering.py
gurux_dlms/GXDLMSChipperingStream.py
gurux_dlms/GXDLMSClient.py
gurux_dlms/GXDLMSConfirmedServiceError.py
gurux_dlms/GXDLMSConnectionEventArgs.py
gurux_dlms/GXDLMSConverter.py
gurux_dlms/GXDLMSException.py
gurux_dlms/GXDLMSExceptionResponse.py
gurux_dlms/GXDLMSGateway.py
gurux_dlms/GXDLMSLNCommandHandler.py
gurux_dlms/GXDLMSLNParameters.py
gurux_dlms/GXDLMSLimits.py
gurux_dlms/GXDLMSLongTransaction.py
gurux_dlms/GXDLMSNotify.py
gurux_dlms/GXDLMSSNCommandHandler.py
gurux_dlms/GXDLMSSNParameters.py
gurux_dlms/GXDLMSServer.py
gurux_dlms/GXDLMSSettings.py
gurux_dlms/GXDLMSTranslator.py
gurux_dlms/GXDLMSTranslatorMessage.py
gurux_dlms/GXDLMSTranslatorStructure.py
gurux_dlms/GXDLMSXmlClient.py
gurux_dlms/GXDLMSXmlPdu.py
gurux_dlms/GXDLMSXmlSettings.py
gurux_dlms/GXDate.py
gurux_dlms/GXDateTime.py
gurux_dlms/GXEnum.py
gurux_dlms/GXFloat32.py
gurux_dlms/GXFloat64.py
gurux_dlms/GXHdlcSettings.py
gurux_dlms/GXICipher.py
gurux_dlms/GXInt16.py
gurux_dlms/GXInt32.py
gurux_dlms/GXInt64.py
gurux_dlms/GXInt8.py
gurux_dlms/GXIntEnum.py
gurux_dlms/GXIntFlag.py
gurux_dlms/GXReplyData.py
gurux_dlms/GXSNInfo.py
gurux_dlms/GXSecure.py
gurux_dlms/GXServerReply.py
gurux_dlms/GXStandardObisCode.py
gurux_dlms/GXStandardObisCodeCollection.py
gurux_dlms/GXStructure.py
gurux_dlms/GXTime.py
gurux_dlms/GXTimeZone.py
gurux_dlms/GXUInt16.py
gurux_dlms/GXUInt32.py
gurux_dlms/GXUInt64.py
gurux_dlms/GXUInt8.py
gurux_dlms/GXWriteItem.py
gurux_dlms/GXXmlLoadSettings.py
gurux_dlms/GetCommandType.py
gurux_dlms/HdlcControlFrame.py
gurux_dlms/IGXCryptoNotifier.py
gurux_dlms/India.txt
gurux_dlms/Italy.txt
gurux_dlms-1.0.196.dist-info/licenses/LICENSE
gurux_dlms-1.0.196.dist-info/METADATA
gurux_dlms-1.0.196.dist-info/WHEEL
gurux_dlms-1.0.196.dist-info/top_level.txt
gurux_dlms-1.0.196.dist-info/RECORD
